messages/__init__.py
messages/messages.py
cuke_messages-0.1.0.dist-info/METADATA
cuke_messages-0.1.0.dist-info/WHEEL
cuke_messages-0.1.0.dist-info/top_level.txt
cuke_messages-0.1.0.dist-info/RECORD
